<appearance>
  <name>print_dialog</name>
  <default>theme</default>
  <field>
    <name>printer_remote_font</name>
    <descr><![CDATA[
Font of names of remote printers.
]]></descr>
    <type>font_arg</type>
  </field>
  <field>
    <name>printer_local_font</name>
    <descr><![CDATA[
Font of names of local printers.
]]></descr>
    <type>font_arg</type>
  </field>
  <field>
    <name>printer_make_and_model_font</name>
    <descr><![CDATA[
Font of printer make and model
]]></descr>
    <type>font_arg</type>
  </field>
  <field>
    <name>printer_location_font</name>
    <descr><![CDATA[
Font of printer locations
]]></descr>
    <type>font_arg</type>
  </field>
  <field>
    <name>printer_status_font</name>
    <descr><![CDATA[
Font of printer status
]]></descr>
    <type>font_arg</type>
  </field>
</appearance>
